implant/__init__.py
implant/connect.py
implant/core.py
implant/logging.yaml
implant/master.py
implant/msgpack.py
implant/pool.py
implant/remote-logging.yaml
implant/scripts.py
implant/testing.py
implant/bootstrap/__init__.py
implant/bootstrap/_main.py.fmt
implant/bootstrap/_with_venv.py.fmt
implant/commands/__init__.py
implant/commands/remotes.py
implant-0.1.2.dist-info/METADATA
implant-0.1.2.dist-info/RECORD
implant-0.1.2.dist-info/WHEEL
implant-0.1.2.dist-info/dependency_links.txt
implant-0.1.2.dist-info/entry_points.txt
implant-0.1.2.dist-info/top_level.txt
