Metadata-Version: 2.1
Name: implant
Version: 0.1.2
Summary: Remote execution via stdin/stdout messaging.
Home-page: https://github.com/diefans/implant
Author: Oliver Berger
Author-email: diefans@gmail.com
License: Apache License Version 2.0
Keywords: asyncio ssh RPC Remote execution dependency injection stdin stdout messaging
Platform: UNKNOWN
Classifier: Development Status :: 4 - Beta
Classifier: License :: OSI Approved :: Apache Software License
Classifier: Intended Audience :: Developers
Classifier: Programming Language :: Python
Classifier: Programming Language :: Python :: 3
Classifier: Programming Language :: Python :: 3.5
Classifier: Programming Language :: Python :: 3.6
Classifier: Programming Language :: Python :: 3.7
Classifier: Topic :: Internet :: WWW/HTTP
Classifier: Framework :: AsyncIO
Requires-Python: >= 3.5.0.0, < 4.0.1.2
Provides-Extra: docs
Provides-Extra: tokio
Provides-Extra: uvloop
Provides-Extra: dev
Requires-Dist: click
Requires-Dist: ruamel.yaml (==0.15.37)
Provides-Extra: dev
Requires-Dist: async-generator; extra == 'dev'
Requires-Dist: pytest; extra == 'dev'
Requires-Dist: pytest-cache; extra == 'dev'
Requires-Dist: pytest-asyncio; extra == 'dev'
Requires-Dist: pytest-random; extra == 'dev'
Requires-Dist: pytest-cov; extra == 'dev'
Requires-Dist: pytest-benchmark; extra == 'dev'
Requires-Dist: pytest-watch; extra == 'dev'
Requires-Dist: pytest-testmon; extra == 'dev'
Requires-Dist: pylama; extra == 'dev'
Requires-Dist: pylama-pylint; extra == 'dev'
Requires-Dist: pycodestyle; extra == 'dev'
Requires-Dist: pydocstyle; extra == 'dev'
Requires-Dist: radon; extra == 'dev'
Requires-Dist: isort; extra == 'dev'
Requires-Dist: ipython; extra == 'dev'
Requires-Dist: pdbpp; extra == 'dev'
Requires-Dist: colorlog; extra == 'dev'
Requires-Dist: tox; extra == 'dev'
Provides-Extra: docs
Requires-Dist: sphinx; extra == 'docs'
Requires-Dist: sphinxcontrib-asyncio; extra == 'docs'
Requires-Dist: sphinxcontrib-fulltoc; extra == 'docs'
Requires-Dist: humanfriendly; extra == 'docs'
Provides-Extra: tokio
Requires-Dist: tokio (==0.99.0); extra == 'tokio'
Provides-Extra: uvloop
Requires-Dist: uvloop; extra == 'uvloop'
